cocojamboo/__init__.py
cocojamboo/coco_eval2.py
cocojamboo/coco_utils.py
cocojamboo/cocoeval2.py
cocojamboo/engine2.py
cocojamboo/transforms.py
cocojamboo/utils.py
cocojamboo-2.1.2.dist-info/LICENSE
cocojamboo-2.1.2.dist-info/METADATA
cocojamboo-2.1.2.dist-info/WHEEL
cocojamboo-2.1.2.dist-info/top_level.txt
cocojamboo-2.1.2.dist-info/RECORD
