Metadata-Version: 2.1
Name: cocojamboo
Version: 2.1.2
Summary: An extension to COCO evaluation metric to provide mAP scores with custom paramters.
Author: Georgiana Manolache
License: 
Project-URL: Homepage, https://gitlab.com/georgianagmanolache/cocojamboo
Keywords: coco metric,coco,coco evaluator
Classifier: License :: Free for non-commercial use
Classifier: Programming Language :: Python
Classifier: Programming Language :: Python :: 3
Requires-Python: >=3.8
License-File: LICENSE
